alibabacloud_anytrans20250707/__init__.py
alibabacloud_anytrans20250707/client.py
alibabacloud_anytrans20250707/models/__init__.py
alibabacloud_anytrans20250707/models/_batch_translate_for_html_request.py
alibabacloud_anytrans20250707/models/_batch_translate_for_html_response.py
alibabacloud_anytrans20250707/models/_batch_translate_for_html_response_body.py
alibabacloud_anytrans20250707/models/_batch_translate_for_html_shrink_request.py
alibabacloud_anytrans20250707/models/_batch_translate_request.py
alibabacloud_anytrans20250707/models/_batch_translate_response.py
alibabacloud_anytrans20250707/models/_batch_translate_response_body.py
alibabacloud_anytrans20250707/models/_batch_translate_shrink_request.py
alibabacloud_anytrans20250707/models/_get_doc_translate_task_request.py
alibabacloud_anytrans20250707/models/_get_doc_translate_task_response.py
alibabacloud_anytrans20250707/models/_get_doc_translate_task_response_body.py
alibabacloud_anytrans20250707/models/_get_html_translate_task_request.py
alibabacloud_anytrans20250707/models/_get_html_translate_task_response.py
alibabacloud_anytrans20250707/models/_get_html_translate_task_response_body.py
alibabacloud_anytrans20250707/models/_get_image_translate_task_request.py
alibabacloud_anytrans20250707/models/_get_image_translate_task_response.py
alibabacloud_anytrans20250707/models/_get_image_translate_task_response_body.py
alibabacloud_anytrans20250707/models/_get_long_text_translate_task_request.py
alibabacloud_anytrans20250707/models/_get_long_text_translate_task_response.py
alibabacloud_anytrans20250707/models/_get_long_text_translate_task_response_body.py
alibabacloud_anytrans20250707/models/_submit_doc_translate_task_request.py
alibabacloud_anytrans20250707/models/_submit_doc_translate_task_response.py
alibabacloud_anytrans20250707/models/_submit_doc_translate_task_response_body.py
alibabacloud_anytrans20250707/models/_submit_doc_translate_task_shrink_request.py
alibabacloud_anytrans20250707-2.1.2.dist-info/LICENSE
alibabacloud_anytrans20250707-2.1.2.dist-info/METADATA
alibabacloud_anytrans20250707-2.1.2.dist-info/WHEEL
alibabacloud_anytrans20250707-2.1.2.dist-info/top_level.txt
alibabacloud_anytrans20250707-2.1.2.dist-info/RECORD
